jamz/__init__.py
jamz/jamz.py
jamz-1.2.1.dist-info/entry_points.txt
jamz-1.2.1.dist-info/LICENSE.txt
jamz-1.2.1.dist-info/WHEEL
jamz-1.2.1.dist-info/METADATA
jamz-1.2.1.dist-info/RECORD
