Metadata-Version: 2.1
Name: jamz
Version: 1.2.1
Summary: Renames music files based on their tags
Home-page: https://github.com/heldridge/jamz
License: MIT
Author: Harry
Requires-Python: >=3.9,<4.0
Classifier: License :: OSI Approved :: MIT License
Classifier: Programming Language :: Python :: 3
Classifier: Programming Language :: Python :: 3.9
Requires-Dist: mutagen (>=1.45.1,<2.0.0)
Requires-Dist: tabulate (>=0.8.9,<0.9.0)
Project-URL: Repository, https://github.com/heldridge/jamz
